format_text/__init__.py
format_text/format_text.py
format_text-0.1.dist-info/METADATA
format_text-0.1.dist-info/WHEEL
format_text-0.1.dist-info/top_level.txt
format_text-0.1.dist-info/RECORD
