Metadata-Version: 2.1
Name: format-text
Version: 0.1
Summary: A text formatting utility for Notes app
Home-page: https://github.com/yourusername/format_text
Author: Your Name
Author-email: your.email@example.com
Classifier: Programming Language :: Python :: 3
Classifier: License :: OSI Approved :: MIT License
Classifier: Operating System :: OS Independent
Requires-Python: >=3.6
